astro_p3-1.4.11.dist-info/licenses/LICENSE
p3/__init__.py
p3/_version.py
p3/dummy.ini
p3/aoSystem/FourierUtils.py
p3/aoSystem/__init__.py
p3/aoSystem/anisoplanatismModel.py
p3/aoSystem/aoSystem.py
p3/aoSystem/atmosphere.py
p3/aoSystem/createSegmentedModes.py
p3/aoSystem/defineAoSystem.py
p3/aoSystem/deformableMirror.py
p3/aoSystem/detector.py
p3/aoSystem/fourierModel.py
p3/aoSystem/frequencyDomain.py
p3/aoSystem/optics.py
p3/aoSystem/processing.py
p3/aoSystem/pupil.py
p3/aoSystem/rtc.py
p3/aoSystem/segment.py
p3/aoSystem/sensor.py
p3/aoSystem/source.py
p3/aoSystem/spiders.py
p3/aoSystem/telescope.py
p3/aoSystem/zernike.py
p3/aoSystem/_txtFile/ELT_segmentVertices.txt
p3/aoSystem/_txtFile/Keck_segmentVertices.txt
p3/aoSystem/data/20130801_n0004.fits
p3/aoSystem/data/ELT_CALIBRATION/CombinedError_Wavefront_nm.fits
p3/aoSystem/data/ELT_CALIBRATION/EELT480pp0.0813spider.fits
p3/aoSystem/data/KECK_CALIBRATION/KECKAO/keckValidActuatorMap.txt
p3/aoSystem/data/KECK_CALIBRATION/KECKAO/keckValidSubapMap.txt
p3/aoSystem/data/KECK_CALIBRATION/KECK_STAT/keck_piston_modes_200px.fits
p3/aoSystem/data/KECK_CALIBRATION/KECK_STAT/keck_piston_modes_200px_9modes_lr.fits
p3/aoSystem/data/KECK_CALIBRATION/KECK_STAT/keck_piston_modes_200px_all_lr.fits
p3/aoSystem/data/KECK_CALIBRATION/KECK_STAT/keck_piston_waffle_modes_200px.fits
p3/aoSystem/data/KECK_CALIBRATION/KECK_STAT/keck_waffle_200px.fits
p3/aoSystem/data/KECK_CALIBRATION/MASSDIMM/MASSDIMM20170315.dimm.dat
p3/aoSystem/data/KECK_CALIBRATION/MASSDIMM/MASSDIMM20170315.mass.dat
p3/aoSystem/data/KECK_CALIBRATION/MASSDIMM/MASSDIMM20170315.masspro.dat
p3/aoSystem/data/KECK_CALIBRATION/MASSDIMM/20130203/20130203.dimm.dat
p3/aoSystem/data/KECK_CALIBRATION/MASSDIMM/20130203/20130203.mass.dat
p3/aoSystem/data/KECK_CALIBRATION/MASSDIMM/20130203/20130203.masspro.dat
p3/aoSystem/data/KECK_CALIBRATION/MASSDIMM/20130914/20130914.dimm.dat
p3/aoSystem/data/KECK_CALIBRATION/MASSDIMM/20130914/20130914.mass.dat
p3/aoSystem/data/KECK_CALIBRATION/MASSDIMM/20130914/20130914.masspro.dat
astro_p3-1.4.11.dist-info/METADATA
astro_p3-1.4.11.dist-info/WHEEL
astro_p3-1.4.11.dist-info/top_level.txt
astro_p3-1.4.11.dist-info/RECORD
