Metadata-Version: 2.4
Name: astro-p3
Version: 1.4.11
Author: Olivier Beltramo-Martin, Benoit Neichel, Fabio Rossi, Guido Agapito, Cédric Plantet
License: BSD-3-Clause
Project-URL: repository, https://github.com/astro-tiptop/P3
Requires-Python: >=3.7
License-File: LICENSE
Requires-Dist: astropy
Requires-Dist: matplotlib
Requires-Dist: numpy
Requires-Dist: scipy
Requires-Dist: pyyaml
Dynamic: license-file
